vhack/__init__.py
vhack/utils.py
vhack/videos.py
vhack-0.1.0.dist-info/METADATA
vhack-0.1.0.dist-info/WHEEL
vhack-0.1.0.dist-info/top_level.txt
vhack-0.1.0.dist-info/RECORD
