Metadata-Version: 2.1
Name: vhack
Version: 0.1.0
Summary: Consultar los videos de Viepaix sobre python y htb
Author: Santiago Beltran
